cli/__init__.py
cli/main.py
cli/utils/__init__.py
cli/utils/gh_utils.py
git_stacks-0.0.4.dist-info/LICENSE
git_stacks-0.0.4.dist-info/METADATA
git_stacks-0.0.4.dist-info/WHEEL
git_stacks-0.0.4.dist-info/entry_points.txt
git_stacks-0.0.4.dist-info/top_level.txt
git_stacks-0.0.4.dist-info/RECORD
