Metadata-Version: 2.1
Name: git-stacks
Version: 0.0.4
License-File: LICENSE
Requires-Dist: Click
Requires-Dist: GitPython
